{"name": "Root", "children": [{"name": "feature 11 <= 2.0", "children": [{"name": "feature 12 <= 164.0", "children": [{"name": "feature 12 <= 124.0", "children": [{"name": "Predict: 0.0"}]}, {"name": "feature 12 > 124.0", "children": [{"name": "feature 13 <= 2.0", "children": [{"name": "Predict: 0.0"}]}, {"name": "feature 13 > 2.0", "children": [{"name": "Predict: 1.0"}]}]}]}, {"name": "feature 12 > 164.0", "children": [{"name": "feature 12 <= 240.0", "children": [{"name": "feature 1 in {0.0}", "children": [{"name": "Predict: 0.0"}]}, {"name": "feature 1 not in {0.0}", "children": [{"name": "Predict: 0.0"}]}]}, {"name": "feature 12 > 240.0", "children": [{"name": "feature 0 in {0.0}", "children": [{"name": "Predict: 0.0"}]}, {"name": "feature 0 not in {0.0}", "children": [{"name": "Predict: 0.0"}]}]}]}]}, {"name": "feature 11 > 2.0", "children": [{"name": "feature 13 <= 3.0", "children": [{"name": "feature 12 <= 283.0", "children": [{"name": "feature 11 <= 6.0", "children": [{"name": "Predict: 0.0"}]}, {"name": "feature 11 > 6.0", "children": [{"name": "Predict: 1.0"}]}]}, {"name": "feature 12 > 283.0", "children": [{"name": "feature 14 <= 0.0", "children": [{"name": "Predict: 1.0"}]}, {"name": "feature 14 > 0.0", "children": [{"name": "Predict: 0.0"}]}]}]}, {"name": "feature 13 > 3.0", "children": [{"name": "feature 12 <= 219.0", "children": [{"name": "feature 12 <= 213.0", "children": [{"name": "Predict: 0.0"}]}, {"name": "feature 12 > 213.0", "children": [{"name": "Predict: 0.0"}]}]}, {"name": "feature 12 > 219.0", "children": [{"name": "feature 11 <= 4.0", "children": [{"name": "Predict: 0.0"}]}, {"name": "feature 11 > 4.0", "children": [{"name": "Predict: 1.0"}]}]}]}]}]}